mtdlearn/__init__.py
mtdlearn/datasets/__init__.py
mtdlearn/datasets/src.py
mtdlearn/mtd/__init__.py
mtdlearn/mtd/src.py
mtdlearn/preprocessing/__init__.py
mtdlearn/preprocessing/src.py
tests/__init__.py
tests/data_for_tests.py
tests/test_all.py
mtdlearn-0.2.3.dist-info/LICENSE
mtdlearn-0.2.3.dist-info/METADATA
mtdlearn-0.2.3.dist-info/WHEEL
mtdlearn-0.2.3.dist-info/top_level.txt
mtdlearn-0.2.3.dist-info/RECORD
