Metadata-Version: 2.1
Name: mtdlearn
Version: 0.2.3
Summary: Package for training Mixture Transition Distribution (MTD) models
Home-page: https://github.com/PiotrekGa/mtd-learn
Author: Piotr Gabryś
Author-email: piotrek.gabrys@gmail.com
License: MIT
Platform: UNKNOWN
Requires-Dist: joblib (>=0.11)
Requires-Dist: numpy (>=1.18.1)
Requires-Dist: scikit-learn (>=0.19.0)
Provides-Extra: dev
Requires-Dist: pytest (>=5.3.5) ; extra == 'dev'
